[
  {
    "snapshotBranchLink": "https://github.com/firebase/firebase-android-sdk/tree/releases/M137",
    "buildArtifactStatus": "",
    "buildArtifactJobId": "",
    "releaseDate": "2023-10-07T00:00:00.000Z",
    "releaseName": "M136",
    "releaseBranchLink": "https://github.com/firebase/firebase-android-sdk/tree/releases/M137.release",
    "snapshotBranchName": "releases/M137",
    "releaseBranchName": "releases/M137.release",
    "buildArtifactConclusion": "",
    "codeFreezeDate": "2023-09-30T00:00:00.000Z",
    "isComplete": false,
    "buildArtifactLink": "",
    "state": "scheduled",
    "libraries": [],
    "checks": []
  },
  {
    "snapshotBranchLink": "https://github.com/firebase/firebase-android-sdk/tree/releases/M137",
    "buildArtifactStatus": "",
    "buildArtifactJobId": "",
    "releaseDate": "2023-09-07T00:00:00.000Z",
    "releaseName": "M137",
    "releaseBranchLink": "https://github.com/firebase/firebase-android-sdk/tree/releases/M137.release",
    "snapshotBranchName": "releases/M137",
    "releaseBranchName": "releases/M137.release",
    "buildArtifactConclusion": "",
    "codeFreezeDate": "2023-08-30T00:00:00.000Z",
    "isComplete": false,
    "buildArtifactLink": "",
    "state": "scheduled",
    "libraries": [],
    "checks": []
  },
  {
    "snapshotBranchLink": "https://github.com/firebase/firebase-android-sdk/tree/releases/M136",
    "buildArtifactStatus": "",
    "buildArtifactJobId": "",
    "releaseDate": "2023-07-07T00:00:00.000Z",
    "releaseName": "M135",
    "releaseBranchLink": "https://github.com/firebase/firebase-android-sdk/tree/releases/M136.release",
    "snapshotBranchName": "releases/M136",
    "releaseBranchName": "releases/M136.release",
    "buildArtifactConclusion": "",
    "codeFreezeDate": "2023-06-30T00:00:00.000Z",
    "isComplete": false,
    "buildArtifactLink": "",
    "state": "error",
    "libraries": [],
    "checks": []
  },
  {
    "snapshotBranchLink": "https://github.com/firebase/firebase-android-sdk/tree/releases/M134",
    "releaseDate": "2023-07-07T00:00:00.000Z",
    "releaseName": "M134",
    "releaseBranchLink": "https://github.com/firebase/firebase-android-sdk/tree/releases/M134.release",
    "snapshotBranchName": "releases/M134",
    "releaseBranchName": "releases/M134.release",
    "codeFreezeDate": "2023-06-30T00:00:00.000Z",
    "isComplete": true,
    "buildArtifactJobId": 5521893523,
    "buildArtifactStatus": "completed",
    "buildArtifactConclusion": "success",
    "state": "released",
    "buildArtifactLink": "https://github.com/firebase/firebase-android-sdk/actions/runs/5521893523",
    "libraries": [
      {
        "libraryName": "firebase-appdistribution-api/ktx",
        "libraryGroupRelease": true,
        "optedIn": false,
        "releaseID": "WNQtWiwo8pHohpEoy9ab",
        "updatedVersion": "16.0.0-beta09",
        "changes": []
      },
      {
        "libraryName": "firebase-messaging/ktx",
        "libraryGroupRelease": true,
        "optedIn": false,
        "releaseID": "WNQtWiwo8pHohpEoy9ab",
        "updatedVersion": "23.2.0",
        "changes": []
      },
      {
        "libraryName": "firebase-appdistribution",
        "libraryGroupRelease": false,
        "optedIn": false,
        "releaseID": "WNQtWiwo8pHohpEoy9ab",
        "updatedVersion": "16.0.0-beta09",
        "changes": [
          {
            "pullRequestLink": "https://github.com/firebase/firebase-android-sdk/pull/5078",
            "releaseID": "WNQtWiwo8pHohpEoy9ab",
            "author": "GitHub user",
            "libraryID": "Bri4bMRe3P4JnsJlROT6",
            "commitID": "bacb414caadcc435afbe79c5f5e6a3a472badc24",
            "message": "Do not require sign in to use developer mode (#5078)\n\n* Do not require sign in to use developer mode\r\n\r\n* Remove unnecessary strings\r\n\r\n* Java format\r\n\r\n* Store dev mode sign in state separately (#5089)",
            "pullRequestID": "5078",
            "commitLink": "https://github.com/firebase/firebase-android-sdk/commit/bacb414caadcc435afbe79c5f5e6a3a472badc24",
            "commitTitle": "Do not require sign in to use developer mode"
          }
        ]
      },
      {
        "libraryName": "firebase-firestore",
        "libraryGroupRelease": false,
        "optedIn": false,
        "releaseID": "WNQtWiwo8pHohpEoy9ab",
        "updatedVersion": "24.7.0",
        "changes": [
          {
            "pullRequestLink": "https://github.com/firebase/firebase-android-sdk/pull/5088",
            "releaseID": "WNQtWiwo8pHohpEoy9ab",
            "author": "GitHub user",
            "libraryID": "C3pBwbE1qjEDWAvITDGE",
            "commitID": "dd710a7194195321e2407ca02ad383f42b73137f",
            "message": "Sync spec tests with changes from https://github.com/firebase/firebase-js-sdk/pull/7372 (#5088)\n\n",
            "pullRequestID": "5088",
            "commitLink": "https://github.com/firebase/firebase-android-sdk/commit/dd710a7194195321e2407ca02ad383f42b73137f",
            "commitTitle": "Sync spec tests with changes from https://github.com/firebase/firebase-js-sdk/pull/7372"
          },
          {
            "pullRequestLink": "https://github.com/firebase/firebase-android-sdk/pull/5099",
            "releaseID": "WNQtWiwo8pHohpEoy9ab",
            "author": "GitHub user",
            "libraryID": "C3pBwbE1qjEDWAvITDGE",
            "commitID": "e3dc1ad7b1ac889e84300d4faea4f4afea990fd2",
            "message": "Making methods in core.Query that memoize results thread safe. (#5099)\n\n* Making methods in core.Query that memoize results thread safe.",
            "pullRequestID": "5099",
            "commitLink": "https://github.com/firebase/firebase-android-sdk/commit/e3dc1ad7b1ac889e84300d4faea4f4afea990fd2",
            "commitTitle": "Making methods in core.Query that memoize results thread safe."
          }
        ]
      },
      {
        "libraryName": "firebase-config",
        "libraryGroupRelease": true,
        "optedIn": true,
        "releaseID": "WNQtWiwo8pHohpEoy9ab",
        "updatedVersion": "21.4.1",
        "changes": []
      },
      {
        "libraryName": "firebase-firestore/ktx",
        "libraryGroupRelease": false,
        "optedIn": false,
        "releaseID": "WNQtWiwo8pHohpEoy9ab",
        "updatedVersion": "24.7.0",
        "changes": [
          {
            "pullRequestLink": "https://github.com/firebase/firebase-android-sdk/pull/4015",
            "releaseID": "WNQtWiwo8pHohpEoy9ab",
            "author": "GitHub user",
            "libraryID": "RFDYXXiCCCxqtf4Zi0ku",
            "commitID": "e9d0de9e2a54724d9d93528560fd269e4100b4cb",
            "message": "Expose Multi-DB, and add tests. (#4015)\n\n* Expose Multi-DB, and add tests.\r\n\r\n* Undo\r\n\r\n* Add documentation and fix test.\r\n\r\n* Make pretty\r\n\r\n* Prevent public access by making multi-db methods package-private\r\n\r\n* Revert \"Prevent public access by making multi-db methods package-private\"\r\n\r\nThis reverts commit 8fbc22f8de5cc996e4eb59adf585c9ca3f0e3962.\r\n\r\n* Format\r\n\r\n* API\r\n\r\n* Fix method description\r\n\r\n* Changelog\r\n\r\n* Format",
            "pullRequestID": "4015",
            "commitLink": "https://github.com/firebase/firebase-android-sdk/commit/e9d0de9e2a54724d9d93528560fd269e4100b4cb",
            "commitTitle": "Expose Multi-DB, and add tests."
          }
        ]
      },
      {
        "libraryName": "firebase-crashlytics-ndk",
        "libraryGroupRelease": true,
        "optedIn": true,
        "releaseID": "WNQtWiwo8pHohpEoy9ab",
        "updatedVersion": "18.4.0",
        "changes": []
      },
      {
        "libraryName": "firebase-config/ktx",
        "libraryGroupRelease": true,
        "optedIn": true,
        "releaseID": "WNQtWiwo8pHohpEoy9ab",
        "updatedVersion": "21.4.1",
        "changes": []
      },
      {
        "libraryName": "firebase-sessions",
        "libraryGroupRelease": true,
        "optedIn": true,
        "releaseID": "WNQtWiwo8pHohpEoy9ab",
        "updatedVersion": "1.0.0",
        "changes": []
      },
      {
        "libraryName": "firebase-appdistribution-api",
        "libraryGroupRelease": false,
        "optedIn": false,
        "releaseID": "WNQtWiwo8pHohpEoy9ab",
        "updatedVersion": "16.0.0-beta09",
        "changes": [
          {
            "pullRequestLink": "https://github.com/firebase/firebase-android-sdk/pull/5111",
            "releaseID": "WNQtWiwo8pHohpEoy9ab",
            "author": "GitHub user",
            "libraryID": "ZoadHJ9cxYOxiJUHue29",
            "commitID": "68c7f0a88533467cd1347494af9787dcc4f9169a",
            "message": "Update App Distro API CHANGELOG.md (#5111)\n\n* Update App Distro API CHANGELOG.md\r\n\r\n* Update CHANGELOG.md",
            "pullRequestID": "5111",
            "commitLink": "https://github.com/firebase/firebase-android-sdk/commit/68c7f0a88533467cd1347494af9787dcc4f9169a",
            "commitTitle": "Update App Distro API CHANGELOG.md"
          }
        ]
      },
      {
        "libraryName": "firebase-crashlytics/ktx",
        "libraryGroupRelease": true,
        "optedIn": true,
        "releaseID": "WNQtWiwo8pHohpEoy9ab",
        "updatedVersion": "18.4.0",
        "changes": []
      },
      {
        "libraryName": "firebase-messaging-directboot",
        "libraryGroupRelease": true,
        "optedIn": false,
        "releaseID": "WNQtWiwo8pHohpEoy9ab",
        "updatedVersion": "23.2.0",
        "changes": []
      },
      {
        "libraryName": "firebase-messaging",
        "libraryGroupRelease": false,
        "optedIn": false,
        "releaseID": "WNQtWiwo8pHohpEoy9ab",
        "updatedVersion": "23.2.0",
        "changes": [
          {
            "pullRequestLink": "https://github.com/firebase/firebase-android-sdk/pull/5116",
            "releaseID": "WNQtWiwo8pHohpEoy9ab",
            "author": "GitHub user",
            "libraryID": "c3joQIz5XyjsjhrY2vl2",
            "commitID": "3f59750767b213ee1a0fc530763855c46d2fdb98",
            "message": "Update deprecated @VisibleForTesting annotation. (#5116)\n\n* Copied internal update in cl/542673677.",
            "pullRequestID": "5116",
            "commitLink": "https://github.com/firebase/firebase-android-sdk/commit/3f59750767b213ee1a0fc530763855c46d2fdb98",
            "commitTitle": "Update deprecated @VisibleForTesting annotation."
          },
          {
            "pullRequestLink": "https://github.com/firebase/firebase-android-sdk/pull/5112",
            "releaseID": "WNQtWiwo8pHohpEoy9ab",
            "author": "GitHub user",
            "libraryID": "c3joQIz5XyjsjhrY2vl2",
            "commitID": "f2faf0607cfc4ce5022ceaec8be35cbb8d987215",
            "message": "Deprecate send. (#5112)\n\n* Marked send as deprecated since upstream messaging is deprecated.",
            "pullRequestID": "5112",
            "commitLink": "https://github.com/firebase/firebase-android-sdk/commit/f2faf0607cfc4ce5022ceaec8be35cbb8d987215",
            "commitTitle": "Deprecate send."
          },
          {
            "pullRequestLink": "https://github.com/firebase/firebase-android-sdk/pull/5074",
            "releaseID": "WNQtWiwo8pHohpEoy9ab",
            "author": "GitHub user",
            "libraryID": "c3joQIz5XyjsjhrY2vl2",
            "commitID": "f76f6972c553be87349557c12acd0d948a2c315b",
            "message": "Comment out failing messaging tests (#5074)\n\n",
            "pullRequestID": "5074",
            "commitLink": "https://github.com/firebase/firebase-android-sdk/commit/f76f6972c553be87349557c12acd0d948a2c315b",
            "commitTitle": "Comment out failing messaging tests"
          }
        ]
      },
      {
        "libraryName": "firebase-perf",
        "libraryGroupRelease": true,
        "optedIn": true,
        "releaseID": "WNQtWiwo8pHohpEoy9ab",
        "updatedVersion": "20.4.0",
        "changes": []
      },
      {
        "libraryName": "firebase-crashlytics",
        "libraryGroupRelease": true,
        "optedIn": true,
        "releaseID": "WNQtWiwo8pHohpEoy9ab",
        "updatedVersion": "18.4.0",
        "changes": []
      },
      {
        "libraryName": "firebase-perf/ktx",
        "libraryGroupRelease": true,
        "optedIn": true,
        "releaseID": "WNQtWiwo8pHohpEoy9ab",
        "updatedVersion": "20.4.0",
        "changes": []
      }
    ],
    "checks": [
      {
        "conclusion": "failure",
        "releaseID": "WNQtWiwo8pHohpEoy9ab",
        "name": "cla/google",
        "headSHA": "6a4dfdcf6e3f1d504a4118e3390d6d5e5a23f00e",
        "outputTitle": "❌ Missing CLA from one or more contributors",
        "httpsUrl": "https://github.com/firebase/firebase-android-sdk/runs/14950980302",
        "status": "completed"
      },
      {
        "conclusion": "failure",
        "releaseID": "WNQtWiwo8pHohpEoy9ab",
        "name": "build-artifacts",
        "headSHA": "6a4dfdcf6e3f1d504a4118e3390d6d5e5a23f00e",
        "outputTitle": null,
        "httpsUrl": "https://github.com/firebase/firebase-android-sdk/actions/runs/5521893521/jobs/10070674747",
        "status": "completed"
      },
      {
        "conclusion": "success",
        "releaseID": "WNQtWiwo8pHohpEoy9ab",
        "name": "build",
        "headSHA": "6a4dfdcf6e3f1d504a4118e3390d6d5e5a23f00e",
        "outputTitle": null,
        "httpsUrl": "https://github.com/firebase/firebase-android-sdk/actions/runs/5521893520/jobs/10070674760",
        "status": "completed"
      },
      {
        "conclusion": "success",
        "releaseID": "WNQtWiwo8pHohpEoy9ab",
        "name": "build-artifacts",
        "headSHA": "6a4dfdcf6e3f1d504a4118e3390d6d5e5a23f00e",
        "outputTitle": null,
        "httpsUrl": "https://github.com/firebase/firebase-android-sdk/actions/runs/5521893522/jobs/10070674770",
        "status": "completed"
      },
      {
        "conclusion": "success",
        "releaseID": "WNQtWiwo8pHohpEoy9ab",
        "name": "build-artifacts",
        "headSHA": "6a4dfdcf6e3f1d504a4118e3390d6d5e5a23f00e",
        "outputTitle": null,
        "httpsUrl": "https://github.com/firebase/firebase-android-sdk/actions/runs/5521893523/jobs/10070674789",
        "status": "completed"
      },
      {
        "conclusion": "failure",
        "releaseID": "WNQtWiwo8pHohpEoy9ab",
        "name": "build-artifacts",
        "headSHA": "6a4dfdcf6e3f1d504a4118e3390d6d5e5a23f00e",
        "outputTitle": null,
        "httpsUrl": "https://github.com/firebase/firebase-android-sdk/actions/runs/5521893527/jobs/10070675018",
        "status": "completed"
      },
      {
        "conclusion": "success",
        "releaseID": "WNQtWiwo8pHohpEoy9ab",
        "name": "api-information-check",
        "headSHA": "6a4dfdcf6e3f1d504a4118e3390d6d5e5a23f00e",
        "outputTitle": null,
        "httpsUrl": "https://github.com/firebase/firebase-android-sdk/actions/runs/5521893519/jobs/10070675055",
        "status": "completed"
      },
      {
        "conclusion": "success",
        "releaseID": "WNQtWiwo8pHohpEoy9ab",
        "name": "smoke-tests",
        "headSHA": "6a4dfdcf6e3f1d504a4118e3390d6d5e5a23f00e",
        "outputTitle": null,
        "httpsUrl": "https://github.com/firebase/firebase-android-sdk/actions/runs/5521893516/jobs/10070675160",
        "status": "completed"
      },
      {
        "conclusion": "success",
        "releaseID": "WNQtWiwo8pHohpEoy9ab",
        "name": "copyright-check",
        "headSHA": "6a4dfdcf6e3f1d504a4118e3390d6d5e5a23f00e",
        "outputTitle": null,
        "httpsUrl": "https://github.com/firebase/firebase-android-sdk/actions/runs/5521893524/jobs/10070675436",
        "status": "completed"
      },
      {
        "conclusion": "success",
        "releaseID": "WNQtWiwo8pHohpEoy9ab",
        "name": "Coverage",
        "headSHA": "6a4dfdcf6e3f1d504a4118e3390d6d5e5a23f00e",
        "outputTitle": null,
        "httpsUrl": "https://github.com/firebase/firebase-android-sdk/actions/runs/5521893517/jobs/10070675442",
        "status": "completed"
      },
      {
        "conclusion": "success",
        "releaseID": "WNQtWiwo8pHohpEoy9ab",
        "name": "changelog-check",
        "headSHA": "6a4dfdcf6e3f1d504a4118e3390d6d5e5a23f00e",
        "outputTitle": null,
        "httpsUrl": "https://github.com/firebase/firebase-android-sdk/actions/runs/5521893530/jobs/10070675458",
        "status": "completed"
      },
      {
        "conclusion": "failure",
        "releaseID": "WNQtWiwo8pHohpEoy9ab",
        "name": "Size",
        "headSHA": "6a4dfdcf6e3f1d504a4118e3390d6d5e5a23f00e",
        "outputTitle": null,
        "httpsUrl": "https://github.com/firebase/firebase-android-sdk/actions/runs/5521893517/jobs/10070675732",
        "status": "completed"
      },
      {
        "conclusion": "success",
        "releaseID": "WNQtWiwo8pHohpEoy9ab",
        "name": "Determine changed modules",
        "headSHA": "6a4dfdcf6e3f1d504a4118e3390d6d5e5a23f00e",
        "outputTitle": null,
        "httpsUrl": "https://github.com/firebase/firebase-android-sdk/actions/runs/5521893518/jobs/10070675755",
        "status": "completed"
      },
      {
        "conclusion": "skipped",
        "releaseID": "WNQtWiwo8pHohpEoy9ab",
        "name": "Startup Time",
        "headSHA": "6a4dfdcf6e3f1d504a4118e3390d6d5e5a23f00e",
        "outputTitle": null,
        "httpsUrl": "https://github.com/firebase/firebase-android-sdk/actions/runs/5521893517/jobs/10070676004",
        "status": "completed"
      },
      {
        "conclusion": "success",
        "releaseID": "WNQtWiwo8pHohpEoy9ab",
        "name": "Unit Tests (:appcheck)",
        "headSHA": "6a4dfdcf6e3f1d504a4118e3390d6d5e5a23f00e",
        "outputTitle": null,
        "httpsUrl": "https://github.com/firebase/firebase-android-sdk/actions/runs/5521893518/jobs/10070834320",
        "status": "completed"
      },
      {
        "conclusion": "success",
        "releaseID": "WNQtWiwo8pHohpEoy9ab",
        "name": "Unit Tests (:encoders)",
        "headSHA": "6a4dfdcf6e3f1d504a4118e3390d6d5e5a23f00e",
        "outputTitle": null,
        "httpsUrl": "https://github.com/firebase/firebase-android-sdk/actions/runs/5521893518/jobs/10070834564",
        "status": "completed"
      },
      {
        "conclusion": "success",
        "releaseID": "WNQtWiwo8pHohpEoy9ab",
        "name": "Unit Tests (:firebase-abt)",
        "headSHA": "6a4dfdcf6e3f1d504a4118e3390d6d5e5a23f00e",
        "outputTitle": null,
        "httpsUrl": "https://github.com/firebase/firebase-android-sdk/actions/runs/5521893518/jobs/10070834757",
        "status": "completed"
      },
      {
        "conclusion": "success",
        "releaseID": "WNQtWiwo8pHohpEoy9ab",
        "name": "Unit Tests (:firebase-annotations)",
        "headSHA": "6a4dfdcf6e3f1d504a4118e3390d6d5e5a23f00e",
        "outputTitle": null,
        "httpsUrl": "https://github.com/firebase/firebase-android-sdk/actions/runs/5521893518/jobs/10070834961",
        "status": "completed"
      },
      {
        "conclusion": "success",
        "releaseID": "WNQtWiwo8pHohpEoy9ab",
        "name": "Unit Tests (:firebase-appdistribution)",
        "headSHA": "6a4dfdcf6e3f1d504a4118e3390d6d5e5a23f00e",
        "outputTitle": null,
        "httpsUrl": "https://github.com/firebase/firebase-android-sdk/actions/runs/5521893518/jobs/10070835156",
        "status": "completed"
      },
      {
        "conclusion": "success",
        "releaseID": "WNQtWiwo8pHohpEoy9ab",
        "name": "Unit Tests (:firebase-appdistribution-api)",
        "headSHA": "6a4dfdcf6e3f1d504a4118e3390d6d5e5a23f00e",
        "outputTitle": null,
        "httpsUrl": "https://github.com/firebase/firebase-android-sdk/actions/runs/5521893518/jobs/10070835372",
        "status": "completed"
      },
      {
        "conclusion": "success",
        "releaseID": "WNQtWiwo8pHohpEoy9ab",
        "name": "Unit Tests (:firebase-appdistribution-api:ktx)",
        "headSHA": "6a4dfdcf6e3f1d504a4118e3390d6d5e5a23f00e",
        "outputTitle": null,
        "httpsUrl": "https://github.com/firebase/firebase-android-sdk/actions/runs/5521893518/jobs/10070835581",
        "status": "completed"
      },
      {
        "conclusion": "success",
        "releaseID": "WNQtWiwo8pHohpEoy9ab",
        "name": "Unit Tests (:firebase-common)",
        "headSHA": "6a4dfdcf6e3f1d504a4118e3390d6d5e5a23f00e",
        "outputTitle": null,
        "httpsUrl": "https://github.com/firebase/firebase-android-sdk/actions/runs/5521893518/jobs/10070835800",
        "status": "completed"
      },
      {
        "conclusion": "success",
        "releaseID": "WNQtWiwo8pHohpEoy9ab",
        "name": "Unit Tests (:firebase-common:ktx)",
        "headSHA": "6a4dfdcf6e3f1d504a4118e3390d6d5e5a23f00e",
        "outputTitle": null,
        "httpsUrl": "https://github.com/firebase/firebase-android-sdk/actions/runs/5521893518/jobs/10070835988",
        "status": "completed"
      },
      {
        "conclusion": "success",
        "releaseID": "WNQtWiwo8pHohpEoy9ab",
        "name": "Unit Tests (:firebase-components)",
        "headSHA": "6a4dfdcf6e3f1d504a4118e3390d6d5e5a23f00e",
        "outputTitle": null,
        "httpsUrl": "https://github.com/firebase/firebase-android-sdk/actions/runs/5521893518/jobs/10070836178",
        "status": "completed"
      },
      {
        "conclusion": "success",
        "releaseID": "WNQtWiwo8pHohpEoy9ab",
        "name": "Unit Tests (:firebase-config)",
        "headSHA": "6a4dfdcf6e3f1d504a4118e3390d6d5e5a23f00e",
        "outputTitle": null,
        "httpsUrl": "https://github.com/firebase/firebase-android-sdk/actions/runs/5521893518/jobs/10070836418",
        "status": "completed"
      },
      {
        "conclusion": "success",
        "releaseID": "WNQtWiwo8pHohpEoy9ab",
        "name": "Unit Tests (:firebase-config:bandwagoner)",
        "headSHA": "6a4dfdcf6e3f1d504a4118e3390d6d5e5a23f00e",
        "outputTitle": null,
        "httpsUrl": "https://github.com/firebase/firebase-android-sdk/actions/runs/5521893518/jobs/10070836626",
        "status": "completed"
      },
      {
        "conclusion": "success",
        "releaseID": "WNQtWiwo8pHohpEoy9ab",
        "name": "Unit Tests (:firebase-config:ktx)",
        "headSHA": "6a4dfdcf6e3f1d504a4118e3390d6d5e5a23f00e",
        "outputTitle": null,
        "httpsUrl": "https://github.com/firebase/firebase-android-sdk/actions/runs/5521893518/jobs/10070836827",
        "status": "completed"
      },
      {
        "conclusion": "success",
        "releaseID": "WNQtWiwo8pHohpEoy9ab",
        "name": "Unit Tests (:firebase-crashlytics)",
        "headSHA": "6a4dfdcf6e3f1d504a4118e3390d6d5e5a23f00e",
        "outputTitle": null,
        "httpsUrl": "https://github.com/firebase/firebase-android-sdk/actions/runs/5521893518/jobs/10070837029",
        "status": "completed"
      },
      {
        "conclusion": "success",
        "releaseID": "WNQtWiwo8pHohpEoy9ab",
        "name": "Unit Tests (:firebase-crashlytics-ndk)",
        "headSHA": "6a4dfdcf6e3f1d504a4118e3390d6d5e5a23f00e",
        "outputTitle": null,
        "httpsUrl": "https://github.com/firebase/firebase-android-sdk/actions/runs/5521893518/jobs/10070837221",
        "status": "completed"
      },
      {
        "conclusion": "success",
        "releaseID": "WNQtWiwo8pHohpEoy9ab",
        "name": "Unit Tests (:firebase-crashlytics:ktx)",
        "headSHA": "6a4dfdcf6e3f1d504a4118e3390d6d5e5a23f00e",
        "outputTitle": null,
        "httpsUrl": "https://github.com/firebase/firebase-android-sdk/actions/runs/5521893518/jobs/10070837394",
        "status": "completed"
      },
      {
        "conclusion": "success",
        "releaseID": "WNQtWiwo8pHohpEoy9ab",
        "name": "Unit Tests (:firebase-sessions:test-app)",
        "headSHA": "6a4dfdcf6e3f1d504a4118e3390d6d5e5a23f00e",
        "outputTitle": null,
        "httpsUrl": "https://github.com/firebase/firebase-android-sdk/actions/runs/5521893518/jobs/10070837638",
        "status": "completed"
      },
      {
        "conclusion": "success",
        "releaseID": "WNQtWiwo8pHohpEoy9ab",
        "name": "Unit Tests (:firebase-database)",
        "headSHA": "6a4dfdcf6e3f1d504a4118e3390d6d5e5a23f00e",
        "outputTitle": null,
        "httpsUrl": "https://github.com/firebase/firebase-android-sdk/actions/runs/5521893518/jobs/10070837850",
        "status": "completed"
      },
      {
        "conclusion": "success",
        "releaseID": "WNQtWiwo8pHohpEoy9ab",
        "name": "Unit Tests (:firebase-database:ktx)",
        "headSHA": "6a4dfdcf6e3f1d504a4118e3390d6d5e5a23f00e",
        "outputTitle": null,
        "httpsUrl": "https://github.com/firebase/firebase-android-sdk/actions/runs/5521893518/jobs/10070838062",
        "status": "completed"
      },
      {
        "conclusion": "success",
        "releaseID": "WNQtWiwo8pHohpEoy9ab",
        "name": "Unit Tests (:firebase-database-collection)",
        "headSHA": "6a4dfdcf6e3f1d504a4118e3390d6d5e5a23f00e",
        "outputTitle": null,
        "httpsUrl": "https://github.com/firebase/firebase-android-sdk/actions/runs/5521893518/jobs/10070838274",
        "status": "completed"
      },
      {
        "conclusion": "success",
        "releaseID": "WNQtWiwo8pHohpEoy9ab",
        "name": "Unit Tests (:firebase-firestore:ktx)",
        "headSHA": "6a4dfdcf6e3f1d504a4118e3390d6d5e5a23f00e",
        "outputTitle": null,
        "httpsUrl": "https://github.com/firebase/firebase-android-sdk/actions/runs/5521893518/jobs/10070838494",
        "status": "completed"
      },
      {
        "conclusion": "success",
        "releaseID": "WNQtWiwo8pHohpEoy9ab",
        "name": "Unit Tests (:firebase-datatransport)",
        "headSHA": "6a4dfdcf6e3f1d504a4118e3390d6d5e5a23f00e",
        "outputTitle": null,
        "httpsUrl": "https://github.com/firebase/firebase-android-sdk/actions/runs/5521893518/jobs/10070838703",
        "status": "completed"
      },
      {
        "conclusion": "success",
        "releaseID": "WNQtWiwo8pHohpEoy9ab",
        "name": "Unit Tests (:firebase-dynamic-links)",
        "headSHA": "6a4dfdcf6e3f1d504a4118e3390d6d5e5a23f00e",
        "outputTitle": null,
        "httpsUrl": "https://github.com/firebase/firebase-android-sdk/actions/runs/5521893518/jobs/10070838916",
        "status": "completed"
      },
      {
        "conclusion": "success",
        "releaseID": "WNQtWiwo8pHohpEoy9ab",
        "name": "Unit Tests (:firebase-dynamic-links:ktx)",
        "headSHA": "6a4dfdcf6e3f1d504a4118e3390d6d5e5a23f00e",
        "outputTitle": null,
        "httpsUrl": "https://github.com/firebase/firebase-android-sdk/actions/runs/5521893518/jobs/10070839116",
        "status": "completed"
      },
      {
        "conclusion": "success",
        "releaseID": "WNQtWiwo8pHohpEoy9ab",
        "name": "Unit Tests (:firebase-firestore)",
        "headSHA": "6a4dfdcf6e3f1d504a4118e3390d6d5e5a23f00e",
        "outputTitle": null,
        "httpsUrl": "https://github.com/firebase/firebase-android-sdk/actions/runs/5521893518/jobs/10070839300",
        "status": "completed"
      },
      {
        "conclusion": "success",
        "releaseID": "WNQtWiwo8pHohpEoy9ab",
        "name": "Unit Tests (:firebase-functions)",
        "headSHA": "6a4dfdcf6e3f1d504a4118e3390d6d5e5a23f00e",
        "outputTitle": null,
        "httpsUrl": "https://github.com/firebase/firebase-android-sdk/actions/runs/5521893518/jobs/10070839476",
        "status": "completed"
      },
      {
        "conclusion": "success",
        "releaseID": "WNQtWiwo8pHohpEoy9ab",
        "name": "Unit Tests (:firebase-functions:ktx)",
        "headSHA": "6a4dfdcf6e3f1d504a4118e3390d6d5e5a23f00e",
        "outputTitle": null,
        "httpsUrl": "https://github.com/firebase/firebase-android-sdk/actions/runs/5521893518/jobs/10070839672",
        "status": "completed"
      },
      {
        "conclusion": "success",
        "releaseID": "WNQtWiwo8pHohpEoy9ab",
        "name": "Unit Tests (:firebase-inappmessaging)",
        "headSHA": "6a4dfdcf6e3f1d504a4118e3390d6d5e5a23f00e",
        "outputTitle": null,
        "httpsUrl": "https://github.com/firebase/firebase-android-sdk/actions/runs/5521893518/jobs/10070839851",
        "status": "completed"
      },
      {
        "conclusion": "success",
        "releaseID": "WNQtWiwo8pHohpEoy9ab",
        "name": "Unit Tests (:firebase-inappmessaging-display)",
        "headSHA": "6a4dfdcf6e3f1d504a4118e3390d6d5e5a23f00e",
        "outputTitle": null,
        "httpsUrl": "https://github.com/firebase/firebase-android-sdk/actions/runs/5521893518/jobs/10070840081",
        "status": "completed"
      },
      {
        "conclusion": "success",
        "releaseID": "WNQtWiwo8pHohpEoy9ab",
        "name": "Unit Tests (:firebase-inappmessaging:ktx)",
        "headSHA": "6a4dfdcf6e3f1d504a4118e3390d6d5e5a23f00e",
        "outputTitle": null,
        "httpsUrl": "https://github.com/firebase/firebase-android-sdk/actions/runs/5521893518/jobs/10070840276",
        "status": "completed"
      },
      {
        "conclusion": "success",
        "releaseID": "WNQtWiwo8pHohpEoy9ab",
        "name": "Unit Tests (:firebase-inappmessaging-display:ktx)",
        "headSHA": "6a4dfdcf6e3f1d504a4118e3390d6d5e5a23f00e",
        "outputTitle": null,
        "httpsUrl": "https://github.com/firebase/firebase-android-sdk/actions/runs/5521893518/jobs/10070840498",
        "status": "completed"
      },
      {
        "conclusion": "failure",
        "releaseID": "WNQtWiwo8pHohpEoy9ab",
        "name": "Unit Tests (:firebase-installations)",
        "headSHA": "6a4dfdcf6e3f1d504a4118e3390d6d5e5a23f00e",
        "outputTitle": null,
        "httpsUrl": "https://github.com/firebase/firebase-android-sdk/actions/runs/5521893518/jobs/10070840659",
        "status": "completed"
      },
      {
        "conclusion": "success",
        "releaseID": "WNQtWiwo8pHohpEoy9ab",
        "name": "Unit Tests (:firebase-ml-modeldownloader)",
        "headSHA": "6a4dfdcf6e3f1d504a4118e3390d6d5e5a23f00e",
        "outputTitle": null,
        "httpsUrl": "https://github.com/firebase/firebase-android-sdk/actions/runs/5521893518/jobs/10070840867",
        "status": "completed"
      },
      {
        "conclusion": "success",
        "releaseID": "WNQtWiwo8pHohpEoy9ab",
        "name": "Unit Tests (:firebase-installations:ktx)",
        "headSHA": "6a4dfdcf6e3f1d504a4118e3390d6d5e5a23f00e",
        "outputTitle": null,
        "httpsUrl": "https://github.com/firebase/firebase-android-sdk/actions/runs/5521893518/jobs/10070841092",
        "status": "completed"
      },
      {
        "conclusion": "success",
        "releaseID": "WNQtWiwo8pHohpEoy9ab",
        "name": "Unit Tests (:firebase-installations-interop)",
        "headSHA": "6a4dfdcf6e3f1d504a4118e3390d6d5e5a23f00e",
        "outputTitle": null,
        "httpsUrl": "https://github.com/firebase/firebase-android-sdk/actions/runs/5521893518/jobs/10070841268",
        "status": "completed"
      },
      {
        "conclusion": "success",
        "releaseID": "WNQtWiwo8pHohpEoy9ab",
        "name": "Unit Tests (:firebase-messaging)",
        "headSHA": "6a4dfdcf6e3f1d504a4118e3390d6d5e5a23f00e",
        "outputTitle": null,
        "httpsUrl": "https://github.com/firebase/firebase-android-sdk/actions/runs/5521893518/jobs/10070841462",
        "status": "completed"
      },
      {
        "conclusion": "success",
        "releaseID": "WNQtWiwo8pHohpEoy9ab",
        "name": "Unit Tests (:firebase-messaging-directboot)",
        "headSHA": "6a4dfdcf6e3f1d504a4118e3390d6d5e5a23f00e",
        "outputTitle": null,
        "httpsUrl": "https://github.com/firebase/firebase-android-sdk/actions/runs/5521893518/jobs/10070841659",
        "status": "completed"
      },
      {
        "conclusion": "success",
        "releaseID": "WNQtWiwo8pHohpEoy9ab",
        "name": "Unit Tests (:firebase-messaging:ktx)",
        "headSHA": "6a4dfdcf6e3f1d504a4118e3390d6d5e5a23f00e",
        "outputTitle": null,
        "httpsUrl": "https://github.com/firebase/firebase-android-sdk/actions/runs/5521893518/jobs/10070841887",
        "status": "completed"
      },
      {
        "conclusion": "success",
        "releaseID": "WNQtWiwo8pHohpEoy9ab",
        "name": "Unit Tests (:firebase-ml-modeldownloader:ktx)",
        "headSHA": "6a4dfdcf6e3f1d504a4118e3390d6d5e5a23f00e",
        "outputTitle": null,
        "httpsUrl": "https://github.com/firebase/firebase-android-sdk/actions/runs/5521893518/jobs/10070842081",
        "status": "completed"
      },
      {
        "conclusion": "success",
        "releaseID": "WNQtWiwo8pHohpEoy9ab",
        "name": "Unit Tests (:firebase-ml-modeldownloader:ml-data-collection-tests)",
        "headSHA": "6a4dfdcf6e3f1d504a4118e3390d6d5e5a23f00e",
        "outputTitle": null,
        "httpsUrl": "https://github.com/firebase/firebase-android-sdk/actions/runs/5521893518/jobs/10070842244",
        "status": "completed"
      },
      {
        "conclusion": "success",
        "releaseID": "WNQtWiwo8pHohpEoy9ab",
        "name": "Unit Tests (:firebase-perf)",
        "headSHA": "6a4dfdcf6e3f1d504a4118e3390d6d5e5a23f00e",
        "outputTitle": null,
        "httpsUrl": "https://github.com/firebase/firebase-android-sdk/actions/runs/5521893518/jobs/10070842431",
        "status": "completed"
      },
      {
        "conclusion": "success",
        "releaseID": "WNQtWiwo8pHohpEoy9ab",
        "name": "Unit Tests (:firebase-perf:ktx)",
        "headSHA": "6a4dfdcf6e3f1d504a4118e3390d6d5e5a23f00e",
        "outputTitle": null,
        "httpsUrl": "https://github.com/firebase/firebase-android-sdk/actions/runs/5521893518/jobs/10070842619",
        "status": "completed"
      },
      {
        "conclusion": "success",
        "releaseID": "WNQtWiwo8pHohpEoy9ab",
        "name": "Unit Tests (:firebase-sessions)",
        "headSHA": "6a4dfdcf6e3f1d504a4118e3390d6d5e5a23f00e",
        "outputTitle": null,
        "httpsUrl": "https://github.com/firebase/firebase-android-sdk/actions/runs/5521893518/jobs/10070842810",
        "status": "completed"
      },
      {
        "conclusion": "success",
        "releaseID": "WNQtWiwo8pHohpEoy9ab",
        "name": "Unit Tests (:firebase-storage)",
        "headSHA": "6a4dfdcf6e3f1d504a4118e3390d6d5e5a23f00e",
        "outputTitle": null,
        "httpsUrl": "https://github.com/firebase/firebase-android-sdk/actions/runs/5521893518/jobs/10070842977",
        "status": "completed"
      },
      {
        "conclusion": "success",
        "releaseID": "WNQtWiwo8pHohpEoy9ab",
        "name": "Unit Tests (:appcheck:firebase-appcheck-debug-testing)",
        "headSHA": "6a4dfdcf6e3f1d504a4118e3390d6d5e5a23f00e",
        "outputTitle": null,
        "httpsUrl": "https://github.com/firebase/firebase-android-sdk/actions/runs/5521893518/jobs/10070843182",
        "status": "completed"
      },
      {
        "conclusion": "success",
        "releaseID": "WNQtWiwo8pHohpEoy9ab",
        "name": "Unit Tests (:firebase-storage:ktx)",
        "headSHA": "6a4dfdcf6e3f1d504a4118e3390d6d5e5a23f00e",
        "outputTitle": null,
        "httpsUrl": "https://github.com/firebase/firebase-android-sdk/actions/runs/5521893518/jobs/10070843349",
        "status": "completed"
      },
      {
        "conclusion": "success",
        "releaseID": "WNQtWiwo8pHohpEoy9ab",
        "name": "Unit Tests (:integ-testing)",
        "headSHA": "6a4dfdcf6e3f1d504a4118e3390d6d5e5a23f00e",
        "outputTitle": null,
        "httpsUrl": "https://github.com/firebase/firebase-android-sdk/actions/runs/5521893518/jobs/10070843493",
        "status": "completed"
      },
      {
        "conclusion": "success",
        "releaseID": "WNQtWiwo8pHohpEoy9ab",
        "name": "Unit Tests (:appcheck:firebase-appcheck)",
        "headSHA": "6a4dfdcf6e3f1d504a4118e3390d6d5e5a23f00e",
        "outputTitle": null,
        "httpsUrl": "https://github.com/firebase/firebase-android-sdk/actions/runs/5521893518/jobs/10070843661",
        "status": "completed"
      },
      {
        "conclusion": "success",
        "releaseID": "WNQtWiwo8pHohpEoy9ab",
        "name": "Unit Tests (:appcheck:firebase-appcheck-debug)",
        "headSHA": "6a4dfdcf6e3f1d504a4118e3390d6d5e5a23f00e",
        "outputTitle": null,
        "httpsUrl": "https://github.com/firebase/firebase-android-sdk/actions/runs/5521893518/jobs/10070843822",
        "status": "completed"
      },
      {
        "conclusion": "success",
        "releaseID": "WNQtWiwo8pHohpEoy9ab",
        "name": "Unit Tests (:appcheck:firebase-appcheck-playintegrity)",
        "headSHA": "6a4dfdcf6e3f1d504a4118e3390d6d5e5a23f00e",
        "outputTitle": null,
        "httpsUrl": "https://github.com/firebase/firebase-android-sdk/actions/runs/5521893518/jobs/10070843948",
        "status": "completed"
      },
      {
        "conclusion": "success",
        "releaseID": "WNQtWiwo8pHohpEoy9ab",
        "name": "Unit Tests (:appcheck:firebase-appcheck-safetynet)",
        "headSHA": "6a4dfdcf6e3f1d504a4118e3390d6d5e5a23f00e",
        "outputTitle": null,
        "httpsUrl": "https://github.com/firebase/firebase-android-sdk/actions/runs/5521893518/jobs/10070844089",
        "status": "completed"
      },
      {
        "conclusion": "success",
        "releaseID": "WNQtWiwo8pHohpEoy9ab",
        "name": "Unit Tests (:protolite-well-known-types)",
        "headSHA": "6a4dfdcf6e3f1d504a4118e3390d6d5e5a23f00e",
        "outputTitle": null,
        "httpsUrl": "https://github.com/firebase/firebase-android-sdk/actions/runs/5521893518/jobs/10070844298",
        "status": "completed"
      },
      {
        "conclusion": "success",
        "releaseID": "WNQtWiwo8pHohpEoy9ab",
        "name": "Unit Tests (:tools)",
        "headSHA": "6a4dfdcf6e3f1d504a4118e3390d6d5e5a23f00e",
        "outputTitle": null,
        "httpsUrl": "https://github.com/firebase/firebase-android-sdk/actions/runs/5521893518/jobs/10070844497",
        "status": "completed"
      },
      {
        "conclusion": "success",
        "releaseID": "WNQtWiwo8pHohpEoy9ab",
        "name": "Unit Tests (:transport)",
        "headSHA": "6a4dfdcf6e3f1d504a4118e3390d6d5e5a23f00e",
        "outputTitle": null,
        "httpsUrl": "https://github.com/firebase/firebase-android-sdk/actions/runs/5521893518/jobs/10070844672",
        "status": "completed"
      },
      {
        "conclusion": "success",
        "releaseID": "WNQtWiwo8pHohpEoy9ab",
        "name": "Unit Tests (:appcheck:firebase-appcheck:ktx)",
        "headSHA": "6a4dfdcf6e3f1d504a4118e3390d6d5e5a23f00e",
        "outputTitle": null,
        "httpsUrl": "https://github.com/firebase/firebase-android-sdk/actions/runs/5521893518/jobs/10070844829",
        "status": "completed"
      },
      {
        "conclusion": "success",
        "releaseID": "WNQtWiwo8pHohpEoy9ab",
        "name": "Unit Tests (:appcheck:firebase-appcheck-interop)",
        "headSHA": "6a4dfdcf6e3f1d504a4118e3390d6d5e5a23f00e",
        "outputTitle": null,
        "httpsUrl": "https://github.com/firebase/firebase-android-sdk/actions/runs/5521893518/jobs/10070844957",
        "status": "completed"
      },
      {
        "conclusion": "success",
        "releaseID": "WNQtWiwo8pHohpEoy9ab",
        "name": "Unit Tests (:encoders:firebase-decoders-json)",
        "headSHA": "6a4dfdcf6e3f1d504a4118e3390d6d5e5a23f00e",
        "outputTitle": null,
        "httpsUrl": "https://github.com/firebase/firebase-android-sdk/actions/runs/5521893518/jobs/10070845143",
        "status": "completed"
      },
      {
        "conclusion": "success",
        "releaseID": "WNQtWiwo8pHohpEoy9ab",
        "name": "Unit Tests (:encoders:firebase-encoders)",
        "headSHA": "6a4dfdcf6e3f1d504a4118e3390d6d5e5a23f00e",
        "outputTitle": null,
        "httpsUrl": "https://github.com/firebase/firebase-android-sdk/actions/runs/5521893518/jobs/10070845296",
        "status": "completed"
      },
      {
        "conclusion": "success",
        "releaseID": "WNQtWiwo8pHohpEoy9ab",
        "name": "Unit Tests (:encoders:protoc-gen-firebase-encoders:tests)",
        "headSHA": "6a4dfdcf6e3f1d504a4118e3390d6d5e5a23f00e",
        "outputTitle": null,
        "httpsUrl": "https://github.com/firebase/firebase-android-sdk/actions/runs/5521893518/jobs/10070845480",
        "status": "completed"
      },
      {
        "conclusion": "success",
        "releaseID": "WNQtWiwo8pHohpEoy9ab",
        "name": "Unit Tests (:encoders:firebase-encoders-json)",
        "headSHA": "6a4dfdcf6e3f1d504a4118e3390d6d5e5a23f00e",
        "outputTitle": null,
        "httpsUrl": "https://github.com/firebase/firebase-android-sdk/actions/runs/5521893518/jobs/10070845654",
        "status": "completed"
      },
      {
        "conclusion": "success",
        "releaseID": "WNQtWiwo8pHohpEoy9ab",
        "name": "Unit Tests (:encoders:firebase-encoders-processor)",
        "headSHA": "6a4dfdcf6e3f1d504a4118e3390d6d5e5a23f00e",
        "outputTitle": null,
        "httpsUrl": "https://github.com/firebase/firebase-android-sdk/actions/runs/5521893518/jobs/10070845859",
        "status": "completed"
      },
      {
        "conclusion": "success",
        "releaseID": "WNQtWiwo8pHohpEoy9ab",
        "name": "Unit Tests (:encoders:firebase-encoders-proto)",
        "headSHA": "6a4dfdcf6e3f1d504a4118e3390d6d5e5a23f00e",
        "outputTitle": null,
        "httpsUrl": "https://github.com/firebase/firebase-android-sdk/actions/runs/5521893518/jobs/10070846059",
        "status": "completed"
      },
      {
        "conclusion": "success",
        "releaseID": "WNQtWiwo8pHohpEoy9ab",
        "name": "Unit Tests (:transport:transport-backend-cct)",
        "headSHA": "6a4dfdcf6e3f1d504a4118e3390d6d5e5a23f00e",
        "outputTitle": null,
        "httpsUrl": "https://github.com/firebase/firebase-android-sdk/actions/runs/5521893518/jobs/10070846259",
        "status": "completed"
      },
      {
        "conclusion": "success",
        "releaseID": "WNQtWiwo8pHohpEoy9ab",
        "name": "Unit Tests (:transport:transport-runtime)",
        "headSHA": "6a4dfdcf6e3f1d504a4118e3390d6d5e5a23f00e",
        "outputTitle": null,
        "httpsUrl": "https://github.com/firebase/firebase-android-sdk/actions/runs/5521893518/jobs/10070846482",
        "status": "completed"
      },
      {
        "conclusion": "success",
        "releaseID": "WNQtWiwo8pHohpEoy9ab",
        "name": "Unit Tests (:encoders:firebase-encoders-reflective)",
        "headSHA": "6a4dfdcf6e3f1d504a4118e3390d6d5e5a23f00e",
        "outputTitle": null,
        "httpsUrl": "https://github.com/firebase/firebase-android-sdk/actions/runs/5521893518/jobs/10070846668",
        "status": "completed"
      },
      {
        "conclusion": "success",
        "releaseID": "WNQtWiwo8pHohpEoy9ab",
        "name": "Unit Tests (:encoders:protoc-gen-firebase-encoders)",
        "headSHA": "6a4dfdcf6e3f1d504a4118e3390d6d5e5a23f00e",
        "outputTitle": null,
        "httpsUrl": "https://github.com/firebase/firebase-android-sdk/actions/runs/5521893518/jobs/10070846860",
        "status": "completed"
      },
      {
        "conclusion": "success",
        "releaseID": "WNQtWiwo8pHohpEoy9ab",
        "name": "Unit Tests (:firebase-common:data-collection-tests)",
        "headSHA": "6a4dfdcf6e3f1d504a4118e3390d6d5e5a23f00e",
        "outputTitle": null,
        "httpsUrl": "https://github.com/firebase/firebase-android-sdk/actions/runs/5521893518/jobs/10070847067",
        "status": "completed"
      },
      {
        "conclusion": "success",
        "releaseID": "WNQtWiwo8pHohpEoy9ab",
        "name": "Unit Tests (:firebase-components:firebase-dynamic-module-support)",
        "headSHA": "6a4dfdcf6e3f1d504a4118e3390d6d5e5a23f00e",
        "outputTitle": null,
        "httpsUrl": "https://github.com/firebase/firebase-android-sdk/actions/runs/5521893518/jobs/10070847440",
        "status": "completed"
      },
      {
        "conclusion": "success",
        "releaseID": "WNQtWiwo8pHohpEoy9ab",
        "name": "Unit Tests (:firebase-perf:dev-app)",
        "headSHA": "6a4dfdcf6e3f1d504a4118e3390d6d5e5a23f00e",
        "outputTitle": null,
        "httpsUrl": "https://github.com/firebase/firebase-android-sdk/actions/runs/5521893518/jobs/10070847794",
        "status": "completed"
      },
      {
        "conclusion": "success",
        "releaseID": "WNQtWiwo8pHohpEoy9ab",
        "name": "Unit Tests (:firebase-perf:e2e-app)",
        "headSHA": "6a4dfdcf6e3f1d504a4118e3390d6d5e5a23f00e",
        "outputTitle": null,
        "httpsUrl": "https://github.com/firebase/firebase-android-sdk/actions/runs/5521893518/jobs/10070847953",
        "status": "completed"
      },
      {
        "conclusion": "success",
        "releaseID": "WNQtWiwo8pHohpEoy9ab",
        "name": "Unit Tests (:tools:lint)",
        "headSHA": "6a4dfdcf6e3f1d504a4118e3390d6d5e5a23f00e",
        "outputTitle": null,
        "httpsUrl": "https://github.com/firebase/firebase-android-sdk/actions/runs/5521893518/jobs/10070848127",
        "status": "completed"
      },
      {
        "conclusion": "success",
        "releaseID": "WNQtWiwo8pHohpEoy9ab",
        "name": "Unit Tests (:transport:transport-api)",
        "headSHA": "6a4dfdcf6e3f1d504a4118e3390d6d5e5a23f00e",
        "outputTitle": null,
        "httpsUrl": "https://github.com/firebase/firebase-android-sdk/actions/runs/5521893518/jobs/10070848307",
        "status": "completed"
      },
      {
        "conclusion": "success",
        "releaseID": "WNQtWiwo8pHohpEoy9ab",
        "name": "Unit Tests (:transport:transport-runtime-testing)",
        "headSHA": "6a4dfdcf6e3f1d504a4118e3390d6d5e5a23f00e",
        "outputTitle": null,
        "httpsUrl": "https://github.com/firebase/firebase-android-sdk/actions/runs/5521893518/jobs/10070848492",
        "status": "completed"
      },
      {
        "conclusion": "success",
        "releaseID": "WNQtWiwo8pHohpEoy9ab",
        "name": "Instrumentation Tests (:appcheck)",
        "headSHA": "6a4dfdcf6e3f1d504a4118e3390d6d5e5a23f00e",
        "outputTitle": null,
        "httpsUrl": "https://github.com/firebase/firebase-android-sdk/actions/runs/5521893518/jobs/10070849817",
        "status": "completed"
      },
      {
        "conclusion": "success",
        "releaseID": "WNQtWiwo8pHohpEoy9ab",
        "name": "Instrumentation Tests (:encoders)",
        "headSHA": "6a4dfdcf6e3f1d504a4118e3390d6d5e5a23f00e",
        "outputTitle": null,
        "httpsUrl": "https://github.com/firebase/firebase-android-sdk/actions/runs/5521893518/jobs/10070850021",
        "status": "completed"
      },
      {
        "conclusion": "success",
        "releaseID": "WNQtWiwo8pHohpEoy9ab",
        "name": "Instrumentation Tests (:firebase-abt)",
        "headSHA": "6a4dfdcf6e3f1d504a4118e3390d6d5e5a23f00e",
        "outputTitle": null,
        "httpsUrl": "https://github.com/firebase/firebase-android-sdk/actions/runs/5521893518/jobs/10070850245",
        "status": "completed"
      },
      {
        "conclusion": "success",
        "releaseID": "WNQtWiwo8pHohpEoy9ab",
        "name": "Instrumentation Tests (:firebase-annotations)",
        "headSHA": "6a4dfdcf6e3f1d504a4118e3390d6d5e5a23f00e",
        "outputTitle": null,
        "httpsUrl": "https://github.com/firebase/firebase-android-sdk/actions/runs/5521893518/jobs/10070850421",
        "status": "completed"
      },
      {
        "conclusion": "success",
        "releaseID": "WNQtWiwo8pHohpEoy9ab",
        "name": "Instrumentation Tests (:firebase-appdistribution)",
        "headSHA": "6a4dfdcf6e3f1d504a4118e3390d6d5e5a23f00e",
        "outputTitle": null,
        "httpsUrl": "https://github.com/firebase/firebase-android-sdk/actions/runs/5521893518/jobs/10070850617",
        "status": "completed"
      },
      {
        "conclusion": "success",
        "releaseID": "WNQtWiwo8pHohpEoy9ab",
        "name": "Instrumentation Tests (:firebase-appdistribution-api)",
        "headSHA": "6a4dfdcf6e3f1d504a4118e3390d6d5e5a23f00e",
        "outputTitle": null,
        "httpsUrl": "https://github.com/firebase/firebase-android-sdk/actions/runs/5521893518/jobs/10070850814",
        "status": "completed"
      },
      {
        "conclusion": "success",
        "releaseID": "WNQtWiwo8pHohpEoy9ab",
        "name": "Instrumentation Tests (:firebase-appdistribution-api:ktx)",
        "headSHA": "6a4dfdcf6e3f1d504a4118e3390d6d5e5a23f00e",
        "outputTitle": null,
        "httpsUrl": "https://github.com/firebase/firebase-android-sdk/actions/runs/5521893518/jobs/10070850997",
        "status": "completed"
      },
      {
        "conclusion": "success",
        "releaseID": "WNQtWiwo8pHohpEoy9ab",
        "name": "Instrumentation Tests (:firebase-common)",
        "headSHA": "6a4dfdcf6e3f1d504a4118e3390d6d5e5a23f00e",
        "outputTitle": null,
        "httpsUrl": "https://github.com/firebase/firebase-android-sdk/actions/runs/5521893518/jobs/10070851224",
        "status": "completed"
      },
      {
        "conclusion": "success",
        "releaseID": "WNQtWiwo8pHohpEoy9ab",
        "name": "Instrumentation Tests (:firebase-common:ktx)",
        "headSHA": "6a4dfdcf6e3f1d504a4118e3390d6d5e5a23f00e",
        "outputTitle": null,
        "httpsUrl": "https://github.com/firebase/firebase-android-sdk/actions/runs/5521893518/jobs/10070851416",
        "status": "completed"
      },
      {
        "conclusion": "success",
        "releaseID": "WNQtWiwo8pHohpEoy9ab",
        "name": "Instrumentation Tests (:firebase-components)",
        "headSHA": "6a4dfdcf6e3f1d504a4118e3390d6d5e5a23f00e",
        "outputTitle": null,
        "httpsUrl": "https://github.com/firebase/firebase-android-sdk/actions/runs/5521893518/jobs/10070851605",
        "status": "completed"
      },
      {
        "conclusion": "success",
        "releaseID": "WNQtWiwo8pHohpEoy9ab",
        "name": "Instrumentation Tests (:firebase-config)",
        "headSHA": "6a4dfdcf6e3f1d504a4118e3390d6d5e5a23f00e",
        "outputTitle": null,
        "httpsUrl": "https://github.com/firebase/firebase-android-sdk/actions/runs/5521893518/jobs/10070851779",
        "status": "completed"
      },
      {
        "conclusion": "success",
        "releaseID": "WNQtWiwo8pHohpEoy9ab",
        "name": "Instrumentation Tests (:firebase-config:bandwagoner)",
        "headSHA": "6a4dfdcf6e3f1d504a4118e3390d6d5e5a23f00e",
        "outputTitle": null,
        "httpsUrl": "https://github.com/firebase/firebase-android-sdk/actions/runs/5521893518/jobs/10070852011",
        "status": "completed"
      },
      {
        "conclusion": "success",
        "releaseID": "WNQtWiwo8pHohpEoy9ab",
        "name": "Instrumentation Tests (:firebase-config:ktx)",
        "headSHA": "6a4dfdcf6e3f1d504a4118e3390d6d5e5a23f00e",
        "outputTitle": null,
        "httpsUrl": "https://github.com/firebase/firebase-android-sdk/actions/runs/5521893518/jobs/10070852239",
        "status": "completed"
      },
      {
        "conclusion": "success",
        "releaseID": "WNQtWiwo8pHohpEoy9ab",
        "name": "Instrumentation Tests (:firebase-crashlytics)",
        "headSHA": "6a4dfdcf6e3f1d504a4118e3390d6d5e5a23f00e",
        "outputTitle": null,
        "httpsUrl": "https://github.com/firebase/firebase-android-sdk/actions/runs/5521893518/jobs/10070852455",
        "status": "completed"
      },
      {
        "conclusion": "success",
        "releaseID": "WNQtWiwo8pHohpEoy9ab",
        "name": "Instrumentation Tests (:firebase-crashlytics-ndk)",
        "headSHA": "6a4dfdcf6e3f1d504a4118e3390d6d5e5a23f00e",
        "outputTitle": null,
        "httpsUrl": "https://github.com/firebase/firebase-android-sdk/actions/runs/5521893518/jobs/10070852686",
        "status": "completed"
      },
      {
        "conclusion": "success",
        "releaseID": "WNQtWiwo8pHohpEoy9ab",
        "name": "Instrumentation Tests (:firebase-crashlytics:ktx)",
        "headSHA": "6a4dfdcf6e3f1d504a4118e3390d6d5e5a23f00e",
        "outputTitle": null,
        "httpsUrl": "https://github.com/firebase/firebase-android-sdk/actions/runs/5521893518/jobs/10070852942",
        "status": "completed"
      },
      {
        "conclusion": "success",
        "releaseID": "WNQtWiwo8pHohpEoy9ab",
        "name": "Instrumentation Tests (:firebase-sessions:test-app)",
        "headSHA": "6a4dfdcf6e3f1d504a4118e3390d6d5e5a23f00e",
        "outputTitle": null,
        "httpsUrl": "https://github.com/firebase/firebase-android-sdk/actions/runs/5521893518/jobs/10070853172",
        "status": "completed"
      },
      {
        "conclusion": "failure",
        "releaseID": "WNQtWiwo8pHohpEoy9ab",
        "name": "Instrumentation Tests (:firebase-database)",
        "headSHA": "6a4dfdcf6e3f1d504a4118e3390d6d5e5a23f00e",
        "outputTitle": null,
        "httpsUrl": "https://github.com/firebase/firebase-android-sdk/actions/runs/5521893518/jobs/10070853356",
        "status": "completed"
      },
      {
        "conclusion": "success",
        "releaseID": "WNQtWiwo8pHohpEoy9ab",
        "name": "Instrumentation Tests (:firebase-database:ktx)",
        "headSHA": "6a4dfdcf6e3f1d504a4118e3390d6d5e5a23f00e",
        "outputTitle": null,
        "httpsUrl": "https://github.com/firebase/firebase-android-sdk/actions/runs/5521893518/jobs/10070853588",
        "status": "completed"
      },
      {
        "conclusion": "success",
        "releaseID": "WNQtWiwo8pHohpEoy9ab",
        "name": "Instrumentation Tests (:firebase-database-collection)",
        "headSHA": "6a4dfdcf6e3f1d504a4118e3390d6d5e5a23f00e",
        "outputTitle": null,
        "httpsUrl": "https://github.com/firebase/firebase-android-sdk/actions/runs/5521893518/jobs/10070853855",
        "status": "completed"
      },
      {
        "conclusion": "success",
        "releaseID": "WNQtWiwo8pHohpEoy9ab",
        "name": "Instrumentation Tests (:firebase-firestore:ktx)",
        "headSHA": "6a4dfdcf6e3f1d504a4118e3390d6d5e5a23f00e",
        "outputTitle": null,
        "httpsUrl": "https://github.com/firebase/firebase-android-sdk/actions/runs/5521893518/jobs/10070854085",
        "status": "completed"
      },
      {
        "conclusion": "success",
        "releaseID": "WNQtWiwo8pHohpEoy9ab",
        "name": "Instrumentation Tests (:firebase-datatransport)",
        "headSHA": "6a4dfdcf6e3f1d504a4118e3390d6d5e5a23f00e",
        "outputTitle": null,
        "httpsUrl": "https://github.com/firebase/firebase-android-sdk/actions/runs/5521893518/jobs/10070854321",
        "status": "completed"
      },
      {
        "conclusion": "success",
        "releaseID": "WNQtWiwo8pHohpEoy9ab",
        "name": "Instrumentation Tests (:firebase-dynamic-links)",
        "headSHA": "6a4dfdcf6e3f1d504a4118e3390d6d5e5a23f00e",
        "outputTitle": null,
        "httpsUrl": "https://github.com/firebase/firebase-android-sdk/actions/runs/5521893518/jobs/10070854594",
        "status": "completed"
      },
      {
        "conclusion": "success",
        "releaseID": "WNQtWiwo8pHohpEoy9ab",
        "name": "Instrumentation Tests (:firebase-dynamic-links:ktx)",
        "headSHA": "6a4dfdcf6e3f1d504a4118e3390d6d5e5a23f00e",
        "outputTitle": null,
        "httpsUrl": "https://github.com/firebase/firebase-android-sdk/actions/runs/5521893518/jobs/10070854828",
        "status": "completed"
      },
      {
        "conclusion": "success",
        "releaseID": "WNQtWiwo8pHohpEoy9ab",
        "name": "Instrumentation Tests (:firebase-firestore)",
        "headSHA": "6a4dfdcf6e3f1d504a4118e3390d6d5e5a23f00e",
        "outputTitle": null,
        "httpsUrl": "https://github.com/firebase/firebase-android-sdk/actions/runs/5521893518/jobs/10070855039",
        "status": "completed"
      },
      {
        "conclusion": "success",
        "releaseID": "WNQtWiwo8pHohpEoy9ab",
        "name": "Instrumentation Tests (:firebase-functions)",
        "headSHA": "6a4dfdcf6e3f1d504a4118e3390d6d5e5a23f00e",
        "outputTitle": null,
        "httpsUrl": "https://github.com/firebase/firebase-android-sdk/actions/runs/5521893518/jobs/10070855257",
        "status": "completed"
      },
      {
        "conclusion": "success",
        "releaseID": "WNQtWiwo8pHohpEoy9ab",
        "name": "Instrumentation Tests (:firebase-functions:ktx)",
        "headSHA": "6a4dfdcf6e3f1d504a4118e3390d6d5e5a23f00e",
        "outputTitle": null,
        "httpsUrl": "https://github.com/firebase/firebase-android-sdk/actions/runs/5521893518/jobs/10070855496",
        "status": "completed"
      },
      {
        "conclusion": "success",
        "releaseID": "WNQtWiwo8pHohpEoy9ab",
        "name": "Instrumentation Tests (:firebase-inappmessaging)",
        "headSHA": "6a4dfdcf6e3f1d504a4118e3390d6d5e5a23f00e",
        "outputTitle": null,
        "httpsUrl": "https://github.com/firebase/firebase-android-sdk/actions/runs/5521893518/jobs/10070855741",
        "status": "completed"
      },
      {
        "conclusion": "success",
        "releaseID": "WNQtWiwo8pHohpEoy9ab",
        "name": "Instrumentation Tests (:firebase-inappmessaging-display)",
        "headSHA": "6a4dfdcf6e3f1d504a4118e3390d6d5e5a23f00e",
        "outputTitle": null,
        "httpsUrl": "https://github.com/firebase/firebase-android-sdk/actions/runs/5521893518/jobs/10070856005",
        "status": "completed"
      },
      {
        "conclusion": "success",
        "releaseID": "WNQtWiwo8pHohpEoy9ab",
        "name": "Instrumentation Tests (:firebase-inappmessaging:ktx)",
        "headSHA": "6a4dfdcf6e3f1d504a4118e3390d6d5e5a23f00e",
        "outputTitle": null,
        "httpsUrl": "https://github.com/firebase/firebase-android-sdk/actions/runs/5521893518/jobs/10070856260",
        "status": "completed"
      },
      {
        "conclusion": "success",
        "releaseID": "WNQtWiwo8pHohpEoy9ab",
        "name": "Instrumentation Tests (:firebase-inappmessaging-display:ktx)",
        "headSHA": "6a4dfdcf6e3f1d504a4118e3390d6d5e5a23f00e",
        "outputTitle": null,
        "httpsUrl": "https://github.com/firebase/firebase-android-sdk/actions/runs/5521893518/jobs/10070856507",
        "status": "completed"
      },
      {
        "conclusion": "success",
        "releaseID": "WNQtWiwo8pHohpEoy9ab",
        "name": "Instrumentation Tests (:firebase-installations)",
        "headSHA": "6a4dfdcf6e3f1d504a4118e3390d6d5e5a23f00e",
        "outputTitle": null,
        "httpsUrl": "https://github.com/firebase/firebase-android-sdk/actions/runs/5521893518/jobs/10070856750",
        "status": "completed"
      },
      {
        "conclusion": "success",
        "releaseID": "WNQtWiwo8pHohpEoy9ab",
        "name": "Instrumentation Tests (:firebase-ml-modeldownloader)",
        "headSHA": "6a4dfdcf6e3f1d504a4118e3390d6d5e5a23f00e",
        "outputTitle": null,
        "httpsUrl": "https://github.com/firebase/firebase-android-sdk/actions/runs/5521893518/jobs/10070857007",
        "status": "completed"
      },
      {
        "conclusion": "success",
        "releaseID": "WNQtWiwo8pHohpEoy9ab",
        "name": "Instrumentation Tests (:firebase-installations:ktx)",
        "headSHA": "6a4dfdcf6e3f1d504a4118e3390d6d5e5a23f00e",
        "outputTitle": null,
        "httpsUrl": "https://github.com/firebase/firebase-android-sdk/actions/runs/5521893518/jobs/10070857216",
        "status": "completed"
      },
      {
        "conclusion": "success",
        "releaseID": "WNQtWiwo8pHohpEoy9ab",
        "name": "Instrumentation Tests (:firebase-installations-interop)",
        "headSHA": "6a4dfdcf6e3f1d504a4118e3390d6d5e5a23f00e",
        "outputTitle": null,
        "httpsUrl": "https://github.com/firebase/firebase-android-sdk/actions/runs/5521893518/jobs/10070857442",
        "status": "completed"
      },
      {
        "conclusion": "success",
        "releaseID": "WNQtWiwo8pHohpEoy9ab",
        "name": "Instrumentation Tests (:firebase-messaging)",
        "headSHA": "6a4dfdcf6e3f1d504a4118e3390d6d5e5a23f00e",
        "outputTitle": null,
        "httpsUrl": "https://github.com/firebase/firebase-android-sdk/actions/runs/5521893518/jobs/10070857720",
        "status": "completed"
      },
      {
        "conclusion": "success",
        "releaseID": "WNQtWiwo8pHohpEoy9ab",
        "name": "Instrumentation Tests (:firebase-messaging-directboot)",
        "headSHA": "6a4dfdcf6e3f1d504a4118e3390d6d5e5a23f00e",
        "outputTitle": null,
        "httpsUrl": "https://github.com/firebase/firebase-android-sdk/actions/runs/5521893518/jobs/10070857912",
        "status": "completed"
      },
      {
        "conclusion": "success",
        "releaseID": "WNQtWiwo8pHohpEoy9ab",
        "name": "Instrumentation Tests (:firebase-messaging:ktx)",
        "headSHA": "6a4dfdcf6e3f1d504a4118e3390d6d5e5a23f00e",
        "outputTitle": null,
        "httpsUrl": "https://github.com/firebase/firebase-android-sdk/actions/runs/5521893518/jobs/10070858115",
        "status": "completed"
      },
      {
        "conclusion": "success",
        "releaseID": "WNQtWiwo8pHohpEoy9ab",
        "name": "Instrumentation Tests (:firebase-ml-modeldownloader:ktx)",
        "headSHA": "6a4dfdcf6e3f1d504a4118e3390d6d5e5a23f00e",
        "outputTitle": null,
        "httpsUrl": "https://github.com/firebase/firebase-android-sdk/actions/runs/5521893518/jobs/10070858308",
        "status": "completed"
      },
      {
        "conclusion": "success",
        "releaseID": "WNQtWiwo8pHohpEoy9ab",
        "name": "Instrumentation Tests (:firebase-ml-modeldownloader:ml-data-collection-tests)",
        "headSHA": "6a4dfdcf6e3f1d504a4118e3390d6d5e5a23f00e",
        "outputTitle": null,
        "httpsUrl": "https://github.com/firebase/firebase-android-sdk/actions/runs/5521893518/jobs/10070858502",
        "status": "completed"
      },
      {
        "conclusion": "success",
        "releaseID": "WNQtWiwo8pHohpEoy9ab",
        "name": "Instrumentation Tests (:firebase-perf)",
        "headSHA": "6a4dfdcf6e3f1d504a4118e3390d6d5e5a23f00e",
        "outputTitle": null,
        "httpsUrl": "https://github.com/firebase/firebase-android-sdk/actions/runs/5521893518/jobs/10070858718",
        "status": "completed"
      },
      {
        "conclusion": "success",
        "releaseID": "WNQtWiwo8pHohpEoy9ab",
        "name": "Instrumentation Tests (:firebase-perf:ktx)",
        "headSHA": "6a4dfdcf6e3f1d504a4118e3390d6d5e5a23f00e",
        "outputTitle": null,
        "httpsUrl": "https://github.com/firebase/firebase-android-sdk/actions/runs/5521893518/jobs/10070858933",
        "status": "completed"
      },
      {
        "conclusion": "success",
        "releaseID": "WNQtWiwo8pHohpEoy9ab",
        "name": "Instrumentation Tests (:firebase-sessions)",
        "headSHA": "6a4dfdcf6e3f1d504a4118e3390d6d5e5a23f00e",
        "outputTitle": null,
        "httpsUrl": "https://github.com/firebase/firebase-android-sdk/actions/runs/5521893518/jobs/10070859154",
        "status": "completed"
      },
      {
        "conclusion": "success",
        "releaseID": "WNQtWiwo8pHohpEoy9ab",
        "name": "Instrumentation Tests (:firebase-storage)",
        "headSHA": "6a4dfdcf6e3f1d504a4118e3390d6d5e5a23f00e",
        "outputTitle": null,
        "httpsUrl": "https://github.com/firebase/firebase-android-sdk/actions/runs/5521893518/jobs/10070859342",
        "status": "completed"
      },
      {
        "conclusion": "success",
        "releaseID": "WNQtWiwo8pHohpEoy9ab",
        "name": "Instrumentation Tests (:appcheck:firebase-appcheck-debug-testing)",
        "headSHA": "6a4dfdcf6e3f1d504a4118e3390d6d5e5a23f00e",
        "outputTitle": null,
        "httpsUrl": "https://github.com/firebase/firebase-android-sdk/actions/runs/5521893518/jobs/10070859520",
        "status": "completed"
      },
      {
        "conclusion": "success",
        "releaseID": "WNQtWiwo8pHohpEoy9ab",
        "name": "Instrumentation Tests (:firebase-storage:ktx)",
        "headSHA": "6a4dfdcf6e3f1d504a4118e3390d6d5e5a23f00e",
        "outputTitle": null,
        "httpsUrl": "https://github.com/firebase/firebase-android-sdk/actions/runs/5521893518/jobs/10070859752",
        "status": "completed"
      },
      {
        "conclusion": "success",
        "releaseID": "WNQtWiwo8pHohpEoy9ab",
        "name": "Instrumentation Tests (:integ-testing)",
        "headSHA": "6a4dfdcf6e3f1d504a4118e3390d6d5e5a23f00e",
        "outputTitle": null,
        "httpsUrl": "https://github.com/firebase/firebase-android-sdk/actions/runs/5521893518/jobs/10070859960",
        "status": "completed"
      },
      {
        "conclusion": "success",
        "releaseID": "WNQtWiwo8pHohpEoy9ab",
        "name": "Instrumentation Tests (:appcheck:firebase-appcheck)",
        "headSHA": "6a4dfdcf6e3f1d504a4118e3390d6d5e5a23f00e",
        "outputTitle": null,
        "httpsUrl": "https://github.com/firebase/firebase-android-sdk/actions/runs/5521893518/jobs/10070860176",
        "status": "completed"
      },
      {
        "conclusion": "success",
        "releaseID": "WNQtWiwo8pHohpEoy9ab",
        "name": "Instrumentation Tests (:appcheck:firebase-appcheck-debug)",
        "headSHA": "6a4dfdcf6e3f1d504a4118e3390d6d5e5a23f00e",
        "outputTitle": null,
        "httpsUrl": "https://github.com/firebase/firebase-android-sdk/actions/runs/5521893518/jobs/10070860381",
        "status": "completed"
      },
      {
        "conclusion": "success",
        "releaseID": "WNQtWiwo8pHohpEoy9ab",
        "name": "Instrumentation Tests (:appcheck:firebase-appcheck-playintegrity)",
        "headSHA": "6a4dfdcf6e3f1d504a4118e3390d6d5e5a23f00e",
        "outputTitle": null,
        "httpsUrl": "https://github.com/firebase/firebase-android-sdk/actions/runs/5521893518/jobs/10070860588",
        "status": "completed"
      },
      {
        "conclusion": "success",
        "releaseID": "WNQtWiwo8pHohpEoy9ab",
        "name": "Instrumentation Tests (:appcheck:firebase-appcheck-safetynet)",
        "headSHA": "6a4dfdcf6e3f1d504a4118e3390d6d5e5a23f00e",
        "outputTitle": null,
        "httpsUrl": "https://github.com/firebase/firebase-android-sdk/actions/runs/5521893518/jobs/10070860819",
        "status": "completed"
      },
      {
        "conclusion": "success",
        "releaseID": "WNQtWiwo8pHohpEoy9ab",
        "name": "Instrumentation Tests (:protolite-well-known-types)",
        "headSHA": "6a4dfdcf6e3f1d504a4118e3390d6d5e5a23f00e",
        "outputTitle": null,
        "httpsUrl": "https://github.com/firebase/firebase-android-sdk/actions/runs/5521893518/jobs/10070861093",
        "status": "completed"
      },
      {
        "conclusion": "success",
        "releaseID": "WNQtWiwo8pHohpEoy9ab",
        "name": "Instrumentation Tests (:tools)",
        "headSHA": "6a4dfdcf6e3f1d504a4118e3390d6d5e5a23f00e",
        "outputTitle": null,
        "httpsUrl": "https://github.com/firebase/firebase-android-sdk/actions/runs/5521893518/jobs/10070861346",
        "status": "completed"
      },
      {
        "conclusion": "success",
        "releaseID": "WNQtWiwo8pHohpEoy9ab",
        "name": "Instrumentation Tests (:transport)",
        "headSHA": "6a4dfdcf6e3f1d504a4118e3390d6d5e5a23f00e",
        "outputTitle": null,
        "httpsUrl": "https://github.com/firebase/firebase-android-sdk/actions/runs/5521893518/jobs/10070861631",
        "status": "completed"
      },
      {
        "conclusion": "success",
        "releaseID": "WNQtWiwo8pHohpEoy9ab",
        "name": "Instrumentation Tests (:appcheck:firebase-appcheck:ktx)",
        "headSHA": "6a4dfdcf6e3f1d504a4118e3390d6d5e5a23f00e",
        "outputTitle": null,
        "httpsUrl": "https://github.com/firebase/firebase-android-sdk/actions/runs/5521893518/jobs/10070861818",
        "status": "completed"
      },
      {
        "conclusion": "success",
        "releaseID": "WNQtWiwo8pHohpEoy9ab",
        "name": "Instrumentation Tests (:appcheck:firebase-appcheck-interop)",
        "headSHA": "6a4dfdcf6e3f1d504a4118e3390d6d5e5a23f00e",
        "outputTitle": null,
        "httpsUrl": "https://github.com/firebase/firebase-android-sdk/actions/runs/5521893518/jobs/10070862028",
        "status": "completed"
      },
      {
        "conclusion": "success",
        "releaseID": "WNQtWiwo8pHohpEoy9ab",
        "name": "Instrumentation Tests (:encoders:firebase-decoders-json)",
        "headSHA": "6a4dfdcf6e3f1d504a4118e3390d6d5e5a23f00e",
        "outputTitle": null,
        "httpsUrl": "https://github.com/firebase/firebase-android-sdk/actions/runs/5521893518/jobs/10070862231",
        "status": "completed"
      },
      {
        "conclusion": "success",
        "releaseID": "WNQtWiwo8pHohpEoy9ab",
        "name": "Instrumentation Tests (:encoders:firebase-encoders)",
        "headSHA": "6a4dfdcf6e3f1d504a4118e3390d6d5e5a23f00e",
        "outputTitle": null,
        "httpsUrl": "https://github.com/firebase/firebase-android-sdk/actions/runs/5521893518/jobs/10070862463",
        "status": "completed"
      },
      {
        "conclusion": "success",
        "releaseID": "WNQtWiwo8pHohpEoy9ab",
        "name": "Instrumentation Tests (:encoders:protoc-gen-firebase-encoders:tests)",
        "headSHA": "6a4dfdcf6e3f1d504a4118e3390d6d5e5a23f00e",
        "outputTitle": null,
        "httpsUrl": "https://github.com/firebase/firebase-android-sdk/actions/runs/5521893518/jobs/10070862701",
        "status": "completed"
      },
      {
        "conclusion": "success",
        "releaseID": "WNQtWiwo8pHohpEoy9ab",
        "name": "Instrumentation Tests (:encoders:firebase-encoders-json)",
        "headSHA": "6a4dfdcf6e3f1d504a4118e3390d6d5e5a23f00e",
        "outputTitle": null,
        "httpsUrl": "https://github.com/firebase/firebase-android-sdk/actions/runs/5521893518/jobs/10070863050",
        "status": "completed"
      },
      {
        "conclusion": "success",
        "releaseID": "WNQtWiwo8pHohpEoy9ab",
        "name": "Instrumentation Tests (:encoders:firebase-encoders-processor)",
        "headSHA": "6a4dfdcf6e3f1d504a4118e3390d6d5e5a23f00e",
        "outputTitle": null,
        "httpsUrl": "https://github.com/firebase/firebase-android-sdk/actions/runs/5521893518/jobs/10070863617",
        "status": "completed"
      },
      {
        "conclusion": "success",
        "releaseID": "WNQtWiwo8pHohpEoy9ab",
        "name": "Instrumentation Tests (:encoders:firebase-encoders-proto)",
        "headSHA": "6a4dfdcf6e3f1d504a4118e3390d6d5e5a23f00e",
        "outputTitle": null,
        "httpsUrl": "https://github.com/firebase/firebase-android-sdk/actions/runs/5521893518/jobs/10070863821",
        "status": "completed"
      },
      {
        "conclusion": "success",
        "releaseID": "WNQtWiwo8pHohpEoy9ab",
        "name": "Instrumentation Tests (:transport:transport-backend-cct)",
        "headSHA": "6a4dfdcf6e3f1d504a4118e3390d6d5e5a23f00e",
        "outputTitle": null,
        "httpsUrl": "https://github.com/firebase/firebase-android-sdk/actions/runs/5521893518/jobs/10070864069",
        "status": "completed"
      },
      {
        "conclusion": "success",
        "releaseID": "WNQtWiwo8pHohpEoy9ab",
        "name": "Instrumentation Tests (:transport:transport-runtime)",
        "headSHA": "6a4dfdcf6e3f1d504a4118e3390d6d5e5a23f00e",
        "outputTitle": null,
        "httpsUrl": "https://github.com/firebase/firebase-android-sdk/actions/runs/5521893518/jobs/10070864321",
        "status": "completed"
      },
      {
        "conclusion": "success",
        "releaseID": "WNQtWiwo8pHohpEoy9ab",
        "name": "Instrumentation Tests (:encoders:firebase-encoders-reflective)",
        "headSHA": "6a4dfdcf6e3f1d504a4118e3390d6d5e5a23f00e",
        "outputTitle": null,
        "httpsUrl": "https://github.com/firebase/firebase-android-sdk/actions/runs/5521893518/jobs/10070864564",
        "status": "completed"
      },
      {
        "conclusion": "success",
        "releaseID": "WNQtWiwo8pHohpEoy9ab",
        "name": "Instrumentation Tests (:encoders:protoc-gen-firebase-encoders)",
        "headSHA": "6a4dfdcf6e3f1d504a4118e3390d6d5e5a23f00e",
        "outputTitle": null,
        "httpsUrl": "https://github.com/firebase/firebase-android-sdk/actions/runs/5521893518/jobs/10070864769",
        "status": "completed"
      },
      {
        "conclusion": "success",
        "releaseID": "WNQtWiwo8pHohpEoy9ab",
        "name": "Instrumentation Tests (:firebase-common:data-collection-tests)",
        "headSHA": "6a4dfdcf6e3f1d504a4118e3390d6d5e5a23f00e",
        "outputTitle": null,
        "httpsUrl": "https://github.com/firebase/firebase-android-sdk/actions/runs/5521893518/jobs/10070864969",
        "status": "completed"
      },
      {
        "conclusion": "success",
        "releaseID": "WNQtWiwo8pHohpEoy9ab",
        "name": "Instrumentation Tests (:firebase-components:firebase-dynamic-module-support)",
        "headSHA": "6a4dfdcf6e3f1d504a4118e3390d6d5e5a23f00e",
        "outputTitle": null,
        "httpsUrl": "https://github.com/firebase/firebase-android-sdk/actions/runs/5521893518/jobs/10070865226",
        "status": "completed"
      },
      {
        "conclusion": "success",
        "releaseID": "WNQtWiwo8pHohpEoy9ab",
        "name": "Instrumentation Tests (:firebase-perf:dev-app)",
        "headSHA": "6a4dfdcf6e3f1d504a4118e3390d6d5e5a23f00e",
        "outputTitle": null,
        "httpsUrl": "https://github.com/firebase/firebase-android-sdk/actions/runs/5521893518/jobs/10070865433",
        "status": "completed"
      },
      {
        "conclusion": "success",
        "releaseID": "WNQtWiwo8pHohpEoy9ab",
        "name": "Instrumentation Tests (:firebase-perf:e2e-app)",
        "headSHA": "6a4dfdcf6e3f1d504a4118e3390d6d5e5a23f00e",
        "outputTitle": null,
        "httpsUrl": "https://github.com/firebase/firebase-android-sdk/actions/runs/5521893518/jobs/10070865627",
        "status": "completed"
      },
      {
        "conclusion": "success",
        "releaseID": "WNQtWiwo8pHohpEoy9ab",
        "name": "Instrumentation Tests (:tools:lint)",
        "headSHA": "6a4dfdcf6e3f1d504a4118e3390d6d5e5a23f00e",
        "outputTitle": null,
        "httpsUrl": "https://github.com/firebase/firebase-android-sdk/actions/runs/5521893518/jobs/10070865837",
        "status": "completed"
      },
      {
        "conclusion": "success",
        "releaseID": "WNQtWiwo8pHohpEoy9ab",
        "name": "Instrumentation Tests (:transport:transport-api)",
        "headSHA": "6a4dfdcf6e3f1d504a4118e3390d6d5e5a23f00e",
        "outputTitle": null,
        "httpsUrl": "https://github.com/firebase/firebase-android-sdk/actions/runs/5521893518/jobs/10070866020",
        "status": "completed"
      },
      {
        "conclusion": "success",
        "releaseID": "WNQtWiwo8pHohpEoy9ab",
        "name": "Instrumentation Tests (:transport:transport-runtime-testing)",
        "headSHA": "6a4dfdcf6e3f1d504a4118e3390d6d5e5a23f00e",
        "outputTitle": null,
        "httpsUrl": "https://github.com/firebase/firebase-android-sdk/actions/runs/5521893518/jobs/10070866239",
        "status": "completed"
      },
      {
        "conclusion": "failure",
        "releaseID": "WNQtWiwo8pHohpEoy9ab",
        "name": "Unit Tests (matrix)",
        "headSHA": "6a4dfdcf6e3f1d504a4118e3390d6d5e5a23f00e",
        "outputTitle": null,
        "httpsUrl": "https://github.com/firebase/firebase-android-sdk/actions/runs/5521893518/jobs/10071158350",
        "status": "completed"
      },
      {
        "conclusion": "success",
        "releaseID": "WNQtWiwo8pHohpEoy9ab",
        "name": "Publish Tests Results",
        "headSHA": "6a4dfdcf6e3f1d504a4118e3390d6d5e5a23f00e",
        "outputTitle": null,
        "httpsUrl": "https://github.com/firebase/firebase-android-sdk/actions/runs/5521893518/jobs/10071158606",
        "status": "completed"
      },
      {
        "conclusion": "failure",
        "releaseID": "WNQtWiwo8pHohpEoy9ab",
        "name": "Unit Test Results",
        "headSHA": "6a4dfdcf6e3f1d504a4118e3390d6d5e5a23f00e",
        "outputTitle": "1 fail, 21 skipped, 4 934 pass in 37m 2s",
        "httpsUrl": "https://github.com/firebase/firebase-android-sdk/runs/14951650949",
        "status": "completed"
      }
    ]
  }
]
